webu/__init__.py
webu/embed.py
webu/llm.py
webu/browsers/chrome.py
webu/fastapis/styles.py
webu/files/paths.py
webu/ipv6/client.py
webu/ipv6/constants.py
webu/ipv6/database.py
webu/ipv6/route.py
webu/ipv6/server.py
webu/ipv6/session.py
webu/pures/constants.py
webu/pures/html2md.py
webu/pures/math.py
webu/pures/purehtml.py
webu/searches/constants.py
webu/searches/google.py
webu/searches/weibo.py
webu/workers/page.py
webu-0.6.1.2.dist-info/licenses/LICENSE
webu-0.6.1.2.dist-info/METADATA
webu-0.6.1.2.dist-info/WHEEL
webu-0.6.1.2.dist-info/top_level.txt
webu-0.6.1.2.dist-info/RECORD
