Metadata-Version: 2.4
Name: webu
Version: 0.6.1.2
Summary: Web Utils for browsing and scraping
Author: Hansimov
Project-URL: Homepage, https://github.com/Hansimov/webu
Project-URL: Issues, https://github.com/Hansimov/webu/issues
Classifier: Programming Language :: Python :: 3
Classifier: License :: OSI Approved :: MIT License
Classifier: Operating System :: OS Independent
Requires-Python: >=3.6
License-File: LICENSE
Requires-Dist: tclogger
Requires-Dist: DrissionPage
Requires-Dist: pyvirtualdisplay
Requires-Dist: beautifulsoup4
Requires-Dist: requests
Requires-Dist: netifaces
Requires-Dist: fastapi
Requires-Dist: uvicorn
Requires-Dist: numpy
Dynamic: license-file
